{"pathType":0,"dataResult":{"dataSourceID":"1108CCB6-5574-4187-8666-058F1E076B95","dataURL":"file:\/\/\/Users\/vaibhavkulkarni\/Data%20set%20for%20ML\/Currency\/","createdDate":"2025-02-17T16:43:16Z"},"preferredFilename":"Currency","modifiedDate":"2025-02-17T16:43:29Z","title":"Currency","createdDate":"2025-02-17T16:43:16Z","activityEntities":["dataSourceMetrics",[{"event":"dataSourceMetrics","id":"7F6768A5-298D-46E2-A3D9-C026026E6A7B","createdDate":"2025-02-17T16:43:29Z","title":"Data Summary","subtitle":"10 Classes, 57 Items"}],"dataSourceCreated",[{"event":"dataSourceCreated","id":"D8C2038E-3E97-4B3D-A728-7A42E4D568CE","createdDate":"2025-02-17T16:43:16Z","title":"Data Source Created","subtitle":"Currency"}],"dataSourceTrainingStarted",[{"id":"48F83A34-97D3-414F-8B07-91FF1C496934","title":"Used By","subtitle":"Currency 1","event":"dataSourceTrainingStarted","createdDate":"2025-02-17T16:43:29Z"}]],"id":"1108CCB6-5574-4187-8666-058F1E076B95","version":"1.0","dataURL":"file:\/\/\/Users\/vaibhavkulkarni\/Data%20set%20for%20ML\/Currency\/","dataPathRelativeToProjectURL":"..\/..\/Data%20set%20for%20ML\/Currency\/","experimentIDs":["183ED6BD-D380-45C1-A3E0-2D355E706F7D"]}